localstack/sdk/api_client.py
localstack/sdk/api_response.py
localstack/sdk/configuration.py
localstack/sdk/exceptions.py
localstack/sdk/py.typed
localstack/sdk/rest.py
localstack/sdk/api/__init__.py
localstack/sdk/api/aws_api.py
localstack/sdk/api/chaos_api.py
localstack/sdk/api/default_api.py
localstack/sdk/api/localstack_api.py
localstack/sdk/api/pods_api.py
localstack/sdk/api/pro_api.py
localstack/sdk/api/replicator_api.py
localstack/sdk/api/state_api.py
localstack/sdk/models/__init__.py
localstack/sdk/models/action_and_resource.py
localstack/sdk/models/aws_pinpoint_application_id_reference_id_get200_response.py
localstack/sdk/models/check_actions_request.py
localstack/sdk/models/check_actions_request_required_permission_inner.py
localstack/sdk/models/check_actions_response.py
localstack/sdk/models/check_actions_response_source_principal.py
localstack/sdk/models/cloud_watch_metrics.py
localstack/sdk/models/cloud_watch_metrics_metrics_inner.py
localstack/sdk/models/cloud_watch_metrics_metrics_inner_d_inner.py
localstack/sdk/models/cloud_watch_metrics_metrics_inner_d_inner_v.py
localstack/sdk/models/cloud_watch_metrics_metrics_inner_t.py
localstack/sdk/models/cloud_watch_metrics_metrics_inner_v.py
localstack/sdk/models/create_remote_request.py
localstack/sdk/models/delete_ddb_expired_items200_response.py
localstack/sdk/models/fault_rule.py
localstack/sdk/models/fault_rule_error.py
localstack/sdk/models/get_diagnostics200_response.py
localstack/sdk/models/get_diagnostics200_response_logs.py
localstack/sdk/models/get_diagnostics200_response_version.py
localstack/sdk/models/get_diagnostics200_response_version_host.py
localstack/sdk/models/get_diagnostics200_response_version_image_version.py
localstack/sdk/models/get_diagnostics200_response_version_localstack_version.py
localstack/sdk/models/get_features_and_services200_response.py
localstack/sdk/models/get_lambda_runtimes200_response.py
localstack/sdk/models/get_ses_messages200_response.py
localstack_sdk_generated-4.12.0.dist-info/METADATA
localstack_sdk_generated-4.12.0.dist-info/WHEEL
localstack_sdk_generated-4.12.0.dist-info/top_level.txt
localstack_sdk_generated-4.12.0.dist-info/RECORD
