Metadata-Version: 2.4
Name: localstack-sdk-generated
Version: 4.12.0
Summary: LocalStack REST API - Generated Code
Author-email: LocalStack Contributors <info@localstack.cloud>
Requires-Dist: urllib3<3.0.0,>=1.25.3
Requires-Dist: python_dateutil>=2.8.2
Requires-Dist: pydantic>=2
Requires-Dist: typing-extensions>=4.7.1
